leaflux/__init__.py
leaflux/dependencies.py
leaflux/environment.py
leaflux/general.py
leaflux/irradiance.py
leaflux/solar.py
leaflux-0.4.1.dist-info/licenses/LICENSE
test/__init__.py
test/test_environment.py
test/test_general.py
test/test_irradiance.py
test/test_solar.py
leaflux-0.4.1.dist-info/METADATA
leaflux-0.4.1.dist-info/WHEEL
leaflux-0.4.1.dist-info/top_level.txt
leaflux-0.4.1.dist-info/RECORD
